{
  "rules": [
    {"id": 1, "condition": "age < 40 and bmi < 25 and hypertension == 0 and heart_disease == 0 and diabetes == 0 and exercise == 1", "risk_level": "low"},
    {"id": 2, "condition": "age < 40 and bmi < 25 and hypertension == 0 and heart_disease == 0 and diabetes == 0 and exercise == 0", "risk_level": "low"},
    {"id": 3, "condition": "age < 40 and bmi < 25 and hypertension == 0 and heart_disease == 0 and diabetes == 1 and exercise == 1", "risk_level": "medium"},
    {"id": 4, "condition": "age < 40 and bmi < 25 and hypertension == 0 and heart_disease == 0 and diabetes == 1 and exercise == 0", "risk_level": "medium"},
    {"id": 5, "condition": "age < 40 and bmi < 25 and hypertension == 0 and heart_disease == 1 and diabetes == 0 and exercise == 1", "risk_level": "medium"},
    {"id": 6, "condition": "age < 40 and bmi < 25 and hypertension == 0 and heart_disease == 1 and diabetes == 0 and exercise == 0", "risk_level": "medium"},
    {"id": 7, "condition": "age < 40 and bmi < 25 and hypertension == 0 and heart_disease == 1 and diabetes == 1 and exercise == 1", "risk_level": "high"},
    {"id": 8, "condition": "age < 40 and bmi < 25 and hypertension == 0 and heart_disease == 1 and diabetes == 1 and exercise == 0", "risk_level": "high"},
    {"id": 9, "condition": "age < 40 and bmi < 25 and hypertension == 1 and heart_disease == 0 and diabetes == 0 and exercise == 1", "risk_level": "medium"},
    {"id": 10, "condition": "age < 40 and bmi < 25 and hypertension == 1 and heart_disease == 0 and diabetes == 0 and exercise == 0", "risk_level": "medium"},
    {"id": 11, "condition": "age < 40 and bmi < 25 and hypertension == 1 and heart_disease == 0 and diabetes == 1 and exercise == 1", "risk_level": "high"},
    {"id": 12, "condition": "age < 40 and bmi < 25 and hypertension == 1 and heart_disease == 0 and diabetes == 1 and exercise == 0", "risk_level": "high"},
    {"id": 13, "condition": "age < 40 and bmi < 25 and hypertension == 1 and heart_disease == 1 and diabetes == 0 and exercise == 1", "risk_level": "high"},
    {"id": 14, "condition": "age < 40 and bmi < 25 and hypertension == 1 and heart_disease == 1 and diabetes == 0 and exercise == 0", "risk_level": "high"},
    {"id": 15, "condition": "age < 40 and bmi < 25 and hypertension == 1 and heart_disease == 1 and diabetes == 1 and exercise == 1", "risk_level": "high"},
    {"id": 16, "condition": "age < 40 and bmi < 25 and hypertension == 1 and heart_disease == 1 and diabetes == 1 and exercise == 0", "risk_level": "high"},
    {"id": 17, "condition": "age < 40 and bmi >= 25 and bmi <= 30 and hypertension == 0 and heart_disease == 0 and diabetes == 0 and exercise == 1", "risk_level": "low"},
    {"id": 18, "condition": "age < 40 and bmi >= 25 and bmi <= 30 and hypertension == 0 and heart_disease == 0 and diabetes == 0 and exercise == 0", "risk_level": "medium"},
    {"id": 19, "condition": "age < 40 and bmi >= 25 and bmi <= 30 and hypertension == 0 and heart_disease == 0 and diabetes == 1 and exercise == 1", "risk_level": "medium"},
    {"id": 20, "condition": "age < 40 and bmi >= 25 and bmi <= 30 and hypertension == 0 and heart_disease == 0 and diabetes == 1 and exercise == 0", "risk_level": "medium"},
    {"id": 21, "condition": "age < 40 and bmi >= 25 and bmi <= 30 and hypertension == 0 and heart_disease == 1 and diabetes == 0 and exercise == 1", "risk_level": "medium"},
    {"id": 22, "condition": "age < 40 and bmi >= 25 and bmi <= 30 and hypertension == 0 and heart_disease == 1 and diabetes == 0 and exercise == 0", "risk_level": "high"},
    {"id": 23, "condition": "age < 40 and bmi >= 25 and bmi <= 30 and hypertension == 0 and heart_disease == 1 and diabetes == 1 and exercise == 1", "risk_level": "high"},
    {"id": 24, "condition": "age < 40 and bmi >= 25 and bmi <= 30 and hypertension == 0 and heart_disease == 1 and diabetes == 1 and exercise == 0", "risk_level": "high"},
    {"id": 25, "condition": "age < 40 and bmi >= 25 and bmi <= 30 and hypertension == 1 and heart_disease == 0 and diabetes == 0 and exercise == 1", "risk_level": "medium"},
    {"id": 26, "condition": "age < 40 and bmi >= 25 and bmi <= 30 and hypertension == 1 and heart_disease == 0 and diabetes == 0 and exercise == 0", "risk_level": "medium"},
    {"id": 27, "condition": "age < 40 and bmi >= 25 and bmi <= 30 and hypertension == 1 and heart_disease == 0 and diabetes == 1 and exercise == 1", "risk_level": "high"},
    {"id": 28, "condition": "age < 40 and bmi >= 25 and bmi <= 30 and hypertension == 1 and heart_disease == 0 and diabetes == 1 and exercise == 0", "risk_level": "high"},
    {"id": 29, "condition": "age < 40 and bmi >= 25 and bmi <= 30 and hypertension == 1 and heart_disease == 1 and diabetes == 0 and exercise == 1", "risk_level": "high"},
    {"id": 30, "condition": "age < 40 and bmi >= 25 and bmi <= 30 and hypertension == 1 and heart_disease == 1 and diabetes == 0 and exercise == 0", "risk_level": "high"},
    {"id": 31, "condition": "age < 40 and bmi >= 25 and bmi <= 30 and hypertension == 1 and heart_disease == 1 and diabetes == 1 and exercise == 1", "risk_level": "high"},
    {"id": 32, "condition": "age < 40 and bmi >= 25 and bmi <= 30 and hypertension == 1 and heart_disease == 1 and diabetes == 1 and exercise == 0", "risk_level": "high"},
    {"id": 33, "condition": "age < 40 and bmi > 30 and hypertension == 0 and heart_disease == 0 and diabetes == 0 and exercise == 1", "risk_level": "medium"},
    {"id": 34, "condition": "age < 40 and bmi > 30 and hypertension == 0 and heart_disease == 0 and diabetes == 0 and exercise == 0", "risk_level": "medium"},
    {"id": 35, "condition": "age < 40 and bmi > 30 and hypertension == 0 and heart_disease == 0 and diabetes == 1 and exercise == 1", "risk_level": "medium"},
    {"id": 36, "condition": "age < 40 and bmi > 30 and hypertension == 0 and heart_disease == 0 and diabetes == 1 and exercise == 0", "risk_level": "high"},
    {"id": 37, "condition": "age < 40 and bmi > 30 and hypertension == 0 and heart_disease == 1 and diabetes == 0 and exercise == 1", "risk_level": "high"},
    {"id": 38, "condition": "age < 40 and bmi > 30 and hypertension == 0 and heart_disease == 1 and diabetes == 0 and exercise == 0", "risk_level": "high"},
    {"id": 39, "condition": "age < 40 and bmi > 30 and hypertension == 0 and heart_disease == 1 and diabetes == 1 and exercise == 1", "risk_level": "high"},
    {"id": 40, "condition": "age < 40 and bmi > 30 and hypertension == 0 and heart_disease == 1 and diabetes == 1 and exercise == 0", "risk_level": "high"},
    {"id": 41, "condition": "age < 40 and bmi > 30 and hypertension == 1 and heart_disease == 0 and diabetes == 0 and exercise == 1", "risk_level": "medium"},
    {"id": 42, "condition": "age < 40 and bmi > 30 and hypertension == 1 and heart_disease == 0 and diabetes == 0 and exercise == 0", "risk_level": "high"},
    {"id": 43, "condition": "age < 40 and bmi > 30 and hypertension == 1 and heart_disease == 0 and diabetes == 1 and exercise == 1", "risk_level": "high"},
    {"id": 44, "condition": "age < 40 and bmi > 30 and hypertension == 1 and heart_disease == 0 and diabetes == 1 and exercise == 0", "risk_level": "high"},
    {"id": 45, "condition": "age < 40 and bmi > 30 and hypertension == 1 and heart_disease == 1 and diabetes == 0 and exercise == 1", "risk_level": "high"},
    {"id": 46, "condition": "age < 40 and bmi > 30 and hypertension == 1 and heart_disease == 1 and diabetes == 0 and exercise == 0", "risk_level": "high"},
    {"id": 47, "condition": "age < 40 and bmi > 30 and hypertension == 1 and heart_disease == 1 and diabetes == 1 and exercise == 1", "risk_level": "high"},
    {"id": 48, "condition": "age < 40 and bmi > 30 and hypertension == 1 and heart_disease == 1 and diabetes == 1 and exercise == 0", "risk_level": "high"},
    {"id": 49, "condition": "age >= 40 and age <= 55 and bmi < 25 and hypertension == 0 and heart_disease == 0 and diabetes == 0 and exercise == 1", "risk_level": "low"},
    {"id": 50, "condition": "age >= 40 and age <= 55 and bmi < 25 and hypertension == 0 and heart_disease == 0 and diabetes == 0 and exercise == 0", "risk_level": "medium"},
    {"id": 51, "condition": "age >= 40 and age <= 55 and bmi < 25 and hypertension == 0 and heart_disease == 0 and diabetes == 1 and exercise == 1", "risk_level": "medium"},
    {"id": 52, "condition": "age >= 40 and age <= 55 and bmi < 25 and hypertension == 0 and heart_disease == 0 and diabetes == 1 and exercise == 0", "risk_level": "medium"},
    {"id": 53, "condition": "age >= 40 and age <= 55 and bmi < 25 and hypertension == 0 and heart_disease == 1 and diabetes == 0 and exercise == 1", "risk_level": "medium"},
    {"id": 54, "condition": "age >= 40 and age <= 55 and bmi < 25 and hypertension == 0 and heart_disease == 1 and diabetes == 0 and exercise == 0", "risk_level": "high"},
    {"id": 55, "condition": "age >= 40 and age <= 55 and bmi < 25 and hypertension == 0 and heart_disease == 1 and diabetes == 1 and exercise == 1", "risk_level": "high"},
    {"id": 56, "condition": "age >= 40 and age <= 55 and bmi < 25 and hypertension == 0 and heart_disease == 1 and diabetes == 1 and exercise == 0", "risk_level": "high"},
    {"id": 57, "condition": "age >= 40 and age <= 55 and bmi < 25 and hypertension == 1 and heart_disease == 0 and diabetes == 0 and exercise == 1", "risk_level": "medium"},
    {"id": 58, "condition": "age >= 40 and age <= 55 and bmi < 25 and hypertension == 1 and heart_disease == 0 and diabetes == 0 and exercise == 0", "risk_level": "medium"},
    {"id": 59, "condition": "age >= 40 and age <= 55 and bmi < 25 and hypertension == 1 and heart_disease == 0 and diabetes == 1 and exercise == 1", "risk_level": "high"},
    {"id": 60, "condition": "age >= 40 and age <= 55 and bmi < 25 and hypertension == 1 and heart_disease == 0 and diabetes == 1 and exercise == 0", "risk_level": "high"},
    {"id": 61, "condition": "age >= 40 and age <= 55 and bmi < 25 and hypertension == 1 and heart_disease == 1 and diabetes == 0 and exercise == 1", "risk_level": "high"},
    {"id": 62, "condition": "age >= 40 and age <= 55 and bmi < 25 and hypertension == 1 and heart_disease == 1 and diabetes == 0 and exercise == 0", "risk_level": "high"},
    {"id": 63, "condition": "age >= 40 and age <= 55 and bmi < 25 and hypertension == 1 and heart_disease == 1 and diabetes == 1 and exercise == 1", "risk_level": "high"},
    {"id": 64, "condition": "age >= 40 and age <= 55 and bmi < 25 and hypertension == 1 and heart_disease == 1 and diabetes == 1 and exercise == 0", "risk_level": "high"},
    {"id": 65, "condition": "age >= 40 and age <= 55 and bmi >= 25 and bmi <= 30 and hypertension == 0 and heart_disease == 0 and diabetes == 0 and exercise == 1", "risk_level": "medium"},
    {"id": 66, "condition": "age >= 40 and age <= 55 and bmi >= 25 and bmi <= 30 and hypertension == 0 and heart_disease == 0 and diabetes == 0 and exercise == 0", "risk_level": "medium"},
    {"id": 67, "condition": "age >= 40 and age <= 55 and bmi >= 25 and bmi <= 30 and hypertension == 0 and heart_disease == 0 and diabetes == 1 and exercise == 1", "risk_level": "medium"},
    {"id": 68, "condition": "age >= 40 and age <= 55 and bmi >= 25 and bmi <= 30 and hypertension == 0 and heart_disease == 0 and diabetes == 1 and exercise == 0", "risk_level": "high"},
    {"id": 69, "condition": "age >= 40 and age <= 55 and bmi >= 25 and bmi <= 30 and hypertension == 0 and heart_disease == 1 and diabetes == 0 and exercise == 1", "risk_level": "high"},
    {"id": 70, "condition": "age >= 40 and age <= 55 and bmi >= 25 and bmi <= 30 and hypertension == 0 and heart_disease == 1 and diabetes == 0 and exercise == 0", "risk_level": "high"},
    {"id": 71, "condition": "age >= 40 and age <= 55 and bmi >= 25 and bmi <= 30 and hypertension == 0 and heart_disease == 1 and diabetes == 1 and exercise == 1", "risk_level": "high"},
    {"id": 72, "condition": "age >= 40 and age <= 55 and bmi >= 25 and bmi <= 30 and hypertension == 0 and heart_disease == 1 and diabetes == 1 and exercise == 0", "risk_level": "high"},
    {"id": 73, "condition": "age >= 40 and age <= 55 and bmi >= 25 and bmi <= 30 and hypertension == 1 and heart_disease == 0 and diabetes == 0 and exercise == 1", "risk_level": "medium"},
    {"id": 74, "condition": "age >= 40 and age <= 55 and bmi >= 25 and bmi <= 30 and hypertension == 1 and heart_disease == 0 and diabetes == 0 and exercise == 0", "risk_level": "high"},
    {"id": 75, "condition": "age >= 40 and age <= 55 and bmi >= 25 and bmi <= 30 and hypertension == 1 and heart_disease == 0 and diabetes == 1 and exercise == 1", "risk_level": "high"},
    {"id": 76, "condition": "age >= 40 and age <= 55 and bmi >= 25 and bmi <= 30 and hypertension == 1 and heart_disease == 0 and diabetes == 1 and exercise == 0", "risk_level": "high"},
    {"id": 77, "condition": "age >= 40 and age <= 55 and bmi >= 25 and bmi <= 30 and hypertension == 1 and heart_disease == 1 and diabetes == 0 and exercise == 1", "risk_level": "high"},
    {"id": 78, "condition": "age >= 40 and age <= 55 and bmi >= 25 and bmi <= 30 and hypertension == 1 and heart_disease == 1 and diabetes == 0 and exercise == 0", "risk_level": "high"},
    {"id": 79, "condition": "age >= 40 and age <= 55 and bmi >= 25 and bmi <= 30 and hypertension == 1 and heart_disease == 1 and diabetes == 1 and exercise == 1", "risk_level": "high"},
    {"id": 80, "condition": "age >= 40 and age <= 55 and bmi >= 25 and bmi <= 30 and hypertension == 1 and heart_disease == 1 and diabetes == 1 and exercise == 0", "risk_level": "high"},
    {"id": 81, "condition": "age >= 40 and age <= 55 and bmi > 30 and hypertension == 0 and heart_disease == 0 and diabetes == 0 and exercise == 1", "risk_level": "medium"},
    {"id": 82, "condition": "age >= 40 and age <= 55 and bmi > 30 and hypertension == 0 and heart_disease == 0 and diabetes == 0 and exercise == 0", "risk_level": "high"},
    {"id": 83, "condition": "age >= 40 and age <= 55 and bmi > 30 and hypertension == 0 and heart_disease == 0 and diabetes == 1 and exercise == 1", "risk_level": "high"},
    {"id": 84, "condition": "age >= 40 and age <= 55 and bmi > 30 and hypertension == 0 and heart_disease == 0 and diabetes == 1 and exercise == 0", "risk_level": "high"},
    {"id": 85, "condition": "age >= 40 and age <= 55 and bmi > 30 and hypertension == 0 and heart_disease == 1 and diabetes == 0 and exercise == 1", "risk_level": "high"},
    {"id": 86, "condition": "age >= 40 and age <= 55 and bmi > 30 and hypertension == 0 and heart_disease == 1 and diabetes == 0 and exercise == 0", "risk_level": "high"},
    {"id": 87, "condition": "age >= 40 and age <= 55 and bmi > 30 and hypertension == 0 and heart_disease == 1 and diabetes == 1 and exercise == 1", "risk_level": "high"},
    {"id": 88, "condition": "age >= 40 and age <= 55 and bmi > 30 and hypertension == 0 and heart_disease == 1 and diabetes == 1 and exercise == 0", "risk_level": "high"},
    {"id": 89, "condition": "age >= 40 and age <= 55 and bmi > 30 and hypertension == 1 and heart_disease == 0 and diabetes == 0 and exercise == 1", "risk_level": "high"},
    {"id": 90, "condition": "age >= 40 and age <= 55 and bmi > 30 and hypertension == 1 and heart_disease == 0 and diabetes == 0 and exercise == 0", "risk_level": "high"},
    {"id": 91, "condition": "age >= 40 and age <= 55 and bmi > 30 and hypertension == 1 and heart_disease == 0 and diabetes == 1 and exercise == 1", "risk_level": "high"},
    {"id": 92, "condition": "age >= 40 and age <= 55 and bmi > 30 and hypertension == 1 and heart_disease == 0 and diabetes == 1 and exercise == 0", "risk_level": "high"},
    {"id": 93, "condition": "age >= 40 and age <= 55 and bmi > 30 and hypertension == 1 and heart_disease == 1 and diabetes == 0 and exercise == 1", "risk_level": "high"},
    {"id": 94, "condition": "age >= 40 and age <= 55 and bmi > 30 and hypertension == 1 and heart_disease == 1 and diabetes == 0 and exercise == 0", "risk_level": "high"},
    {"id": 95, "condition": "age >= 40 and age <= 55 and bmi > 30 and hypertension == 1 and heart_disease == 1 and diabetes == 1 and exercise == 1", "risk_level": "high"},
    {"id": 96, "condition": "age >= 40 and age <= 55 and bmi > 30 and hypertension == 1 and heart_disease == 1 and diabetes == 1 and exercise == 0", "risk_level": "high"},
    {"id": 97, "condition": "age > 55 and bmi < 25 and hypertension == 0 and heart_disease == 0 and diabetes == 0 and exercise == 1", "risk_level": "low"},
    {"id": 98, "condition": "age > 55 and bmi < 25 and hypertension == 0 and heart_disease == 0 and diabetes == 0 and exercise == 0", "risk_level": "medium"},
    {"id": 99, "condition": "age > 55 and bmi < 25 and hypertension == 0 and heart_disease == 0 and diabetes == 1 and exercise == 1", "risk_level": "medium"},
    {"id": 100, "condition": "age > 55 and bmi < 25 and hypertension == 0 and heart_disease == 0 and diabetes == 1 and exercise == 0", "risk_level": "high"},
    {"id": 101, "condition": "age > 55 and bmi < 25 and hypertension == 0 and heart_disease == 1 and diabetes == 0 and exercise == 1", "risk_level": "high"},
    {"id": 102, "condition": "age > 55 and bmi < 25 and hypertension == 0 and heart_disease == 1 and diabetes == 0 and exercise == 0", "risk_level": "high"},
    {"id": 103, "condition": "age > 55 and bmi < 25 and hypertension == 0 and heart_disease == 1 and diabetes == 1 and exercise == 1", "risk_level": "high"},
    {"id": 104, "condition": "age > 55 and bmi < 25 and hypertension == 0 and heart_disease == 1 and diabetes == 1 and exercise == 0", "risk_level": "high"},
    {"id": 105, "condition": "age > 55 and bmi < 25 and hypertension == 1 and heart_disease == 0 and diabetes == 0 and exercise == 1", "risk_level": "medium"},
    {"id": 106, "condition": "age > 55 and bmi < 25 and hypertension == 1 and heart_disease == 0 and diabetes == 0 and exercise == 0", "risk_level": "high"},
    {"id": 107, "condition": "age > 55 and bmi < 25 and hypertension == 1 and heart_disease == 0 and diabetes == 1 and exercise == 1", "risk_level": "high"},
    {"id": 108, "condition": "age > 55 and bmi < 25 and hypertension == 1 and heart_disease == 0 and diabetes == 1 and exercise == 0", "risk_level": "high"},
    {"id": 109, "condition": "age > 55 and bmi < 25 and hypertension == 1 and heart_disease == 1 and diabetes == 0 and exercise == 1", "risk_level": "high"},
    {"id": 110, "condition": "age > 55 and bmi < 25 and hypertension == 1 and heart_disease == 1 and diabetes == 0 and exercise == 0", "risk_level": "high"},
    {"id": 111, "condition": "age > 55 and bmi < 25 and hypertension == 1 and heart_disease == 1 and diabetes == 1 and exercise == 1", "risk_level": "high"},
    {"id": 112, "condition": "age > 55 and bmi < 25 and hypertension == 1 and heart_disease == 1 and diabetes == 1 and exercise == 0", "risk_level": "high"},
    {"id": 113, "condition": "age > 55 and bmi >= 25 and bmi <= 30 and hypertension == 0 and heart_disease == 0 and diabetes == 0 and exercise == 1", "risk_level": "medium"},
    {"id": 114, "condition": "age > 55 and bmi >= 25 and bmi <= 30 and hypertension == 0 and heart_disease == 0 and diabetes == 0 and exercise == 1", "risk_level": "medium"},
    {"id": 115, "condition": "age > 55 and bmi >= 25 and bmi <= 30 and hypertension == 0 and heart_disease == 0 and diabetes == 0 and exercise == 0", "risk_level": "high"},
    {"id": 116, "condition": "age > 55 and bmi >= 25 and bmi <= 30 and hypertension == 0 and heart_disease == 0 and diabetes == 1 and exercise == 1", "risk_level": "high"},
    {"id": 117, "condition": "age > 55 and bmi >= 25 and bmi <= 30 and hypertension == 0 and heart_disease == 0 and diabetes == 1 and exercise == 0", "risk_level": "high"},
    {"id": 118, "condition": "age > 55 and bmi >= 25 and bmi <= 30 and hypertension == 0 and heart_disease == 1 and diabetes == 0 and exercise == 1", "risk_level": "high"},
    {"id": 119, "condition": "age > 55 and bmi >= 25 and bmi <= 30 and hypertension == 0 and heart_disease == 1 and diabetes == 0 and exercise == 0", "risk_level": "high"},
    {"id": 120, "condition": "age > 55 and bmi >= 25 and bmi <= 30 and hypertension == 0 and heart_disease == 1 and diabetes == 1 and exercise == 1", "risk_level": "high"},
    {"id": 121, "condition": "age > 55 and bmi >= 25 and bmi <= 30 and hypertension == 0 and heart_disease == 1 and diabetes == 1 and exercise == 0", "risk_level": "high"},
    {"id": 122, "condition": "age > 55 and bmi >= 25 and bmi <= 30 and hypertension == 1 and heart_disease == 0 and diabetes == 0 and exercise == 1", "risk_level": "high"},
    {"id": 123, "condition": "age > 55 and bmi >= 25 and bmi <= 30 and hypertension == 1 and heart_disease == 0 and diabetes == 0 and exercise == 0", "risk_level": "high"},
    {"id": 124, "condition": "age > 55 and bmi >= 25 and bmi <= 30 and hypertension == 1 and heart_disease == 0 and diabetes == 1 and exercise == 1", "risk_level": "high"},
    {"id": 125, "condition": "age > 55 and bmi >= 25 and bmi <= 30 and hypertension == 1 and heart_disease == 0 and diabetes == 1 and exercise == 0", "risk_level": "high"},
    {"id": 126, "condition": "age > 55 and bmi >= 25 and bmi <= 30 and hypertension == 1 and heart_disease == 1 and diabetes == 0 and exercise == 1", "risk_level": "high"},
    {"id": 127, "condition": "age > 55 and bmi >= 25 and bmi <= 30 and hypertension == 1 and heart_disease == 1 and diabetes == 0 and exercise == 0", "risk_level": "high"},
    {"id": 128, "condition": "age > 55 and bmi >= 25 and bmi <= 30 and hypertension == 1 and heart_disease == 1 and diabetes == 1 and exercise == 1", "risk_level": "high"},
    {"id": 129, "condition": "age > 55 and bmi >= 25 and bmi <= 30 and hypertension == 1 and heart_disease == 1 and diabetes == 1 and exercise == 0", "risk_level": "high"},
    {"id": 130, "condition": "age > 55 and bmi > 30 and hypertension == 0 and heart_disease == 0 and diabetes == 0 and exercise == 1", "risk_level": "high"},
    {"id": 131, "condition": "age > 55 and bmi > 30 and hypertension == 0 and heart_disease == 0 and diabetes == 0 and exercise == 0", "risk_level": "high"},
    {"id": 132, "condition": "age > 55 and bmi > 30 and hypertension == 0 and heart_disease == 0 and diabetes == 1 and exercise == 1", "risk_level": "high"},
    {"id": 133, "condition": "age > 55 and bmi > 30 and hypertension == 0 and heart_disease == 0 and diabetes == 1 and exercise == 0", "risk_level": "high"},
    {"id": 134, "condition": "age > 55 and bmi > 30 and hypertension == 0 and heart_disease == 1 and diabetes == 0 and exercise == 1", "risk_level": "high"},
    {"id": 135, "condition": "age > 55 and bmi > 30 and hypertension == 0 and heart_disease == 1 and diabetes == 0 and exercise == 0", "risk_level": "high"},
    {"id": 136, "condition": "age > 55 and bmi > 30 and hypertension == 0 and heart_disease == 1 and diabetes == 1 and exercise == 1", "risk_level": "high"},
    {"id": 137, "condition": "age > 55 and bmi > 30 and hypertension == 0 and heart_disease == 1 and diabetes == 1 and exercise == 0", "risk_level": "high"},
    {"id": 138, "condition": "age > 55 and bmi > 30 and hypertension == 1 and heart_disease == 0 and diabetes == 0 and exercise == 1", "risk_level": "high"},
    {"id": 139, "condition": "age > 55 and bmi > 30 and hypertension == 1 and heart_disease == 0 and diabetes == 0 and exercise == 0", "risk_level": "high"},
    {"id": 140, "condition": "age > 55 and bmi > 30 and hypertension == 1 and heart_disease == 0 and diabetes == 1 and exercise == 1", "risk_level": "high"},
    {"id": 141, "condition": "age > 55 and bmi > 30 and hypertension == 1 and heart_disease == 0 and diabetes == 1 and exercise == 0", "risk_level": "high"},
    {"id": 142, "condition": "age > 55 and bmi > 30 and hypertension == 1 and heart_disease == 1 and diabetes == 0 and exercise == 1", "risk_level": "high"},
    {"id": 143, "condition": "age > 55 and bmi > 30 and hypertension == 1 and heart_disease == 1 and diabetes == 0 and exercise == 0", "risk_level": "high"},
    {"id": 144, "condition": "age > 55 and bmi > 30 and hypertension == 1 and heart_disease == 1 and diabetes == 1 and exercise == 1", "risk_level": "high"}
  ],
  "sources": {
    "AHA": "American Heart Association (2023). Understanding stroke risk factors. https://www.heart.org/en/health-topics/stroke/understanding-stroke-risk-factors",
    "Framingham": "D'Agostino, R. B., et al. (2004). Stroke risk profile: The Framingham study. https://pubmed.ncbi.nlm.nih.gov/14718319/",
    "CDC": "Centers for Disease Control and Prevention (2023). Stroke risk factors. https://www.cdc.gov/stroke/risk-factors/index.html",
    "WHO": "World Health Organization (2022). Stroke prevention guidelines. https://www.who.int/health-topics/stroke#tab=tab_1"
  }
}